[{"_path":"/","_dir":"","_draft":false,"_partial":false,"_locale":"","title":"Start","description":"Enter Science: Escape Game ist eine Projektwerkstatt an der Technischen Universität Berlin","layout":"default","head":{"title":"Enter Science: Escape Game"},"_type":"markdown","_id":"content:1.index.md","_source":"content","_file":"1.index.md","_extension":"md"},{"_path":"/kontakt","_dir":"","_draft":false,"_partial":false,"_locale":"","title":"Kontakt","description":"","layout":"default","_type":"markdown","_id":"content:3.kontakt.md","_source":"content","_file":"3.kontakt.md","_extension":"md"}]